pulse_vpn/__init__.py
pulse_vpn/__main__.py
pulse_vpn/main.py
pulse_vpn-0.1.1.dist-info/LICENSE
pulse_vpn-0.1.1.dist-info/METADATA
pulse_vpn-0.1.1.dist-info/WHEEL
pulse_vpn-0.1.1.dist-info/entry_points.txt
pulse_vpn-0.1.1.dist-info/top_level.txt
pulse_vpn-0.1.1.dist-info/RECORD
