Metadata-Version: 2.1
Name: pulse-vpn
Version: 0.1.1
Summary: OpenConnect wrapper for Pulse Secure VPN
Author-email: Borodin Gregory <grihabor@gmail.com>
License: GNU GENERAL PUBLIC LICENSE
Project-URL: repository, https://github.com/grihabor/pulse-vpn
Keywords: vpn,Pulse Secure,openconnect,ivanti
Classifier: Programming Language :: Python :: 3
Requires-Python: >=3.11
License-File: LICENSE
Requires-Dist: PyQt6-WebEngine
